[{"userName":"New weapons","userEmail":"new_weapons@asd","gamePoints":3015,"gameCoins":53450,"userPassword":"12345","id":1585707356975},{"userName":"high result","userEmail":"test@asd","gamePoints":2845,"gameCoins":40300,"userPassword":"12345","id":1585346976058},{"userName":"zen","userEmail":"zen@asd","gamePoints":5311,"gameCoins":31096,"userPassword":"1234567","id":1585006840057},{"userName":"hi rate","userEmail":"test@gmail.com","gamePoints":2175,"gameCoins":34400,"userPassword":"1234","id":1584920929811},{"userName":"adad2","userEmail":"asda@asd1","gamePoints":1050,"gameCoins":15200,"userPassword":"12345","id":1585247429124},{"userName":"adad","userEmail":"asd@ad","gamePoints":1050,"gameCoins":15200,"userPassword":"12345","id":1585247347037},{"userName":"adad1","userEmail":"asda@asd","gamePoints":1050,"gameCoins":15200,"userPassword":"@asda","id":1585247390407}]